textual_shell/__init__.py
textual_shell/app.py
textual_shell/command.py
textual_shell/configure.py
textual_shell/job.py
textual_shell/commands/__init__.py
textual_shell/commands/bash.py
textual_shell/commands/clear.py
textual_shell/commands/help.py
textual_shell/commands/jobs.py
textual_shell/commands/python.py
textual_shell/commands/set.py
textual_shell/widgets/__init__.py
textual_shell/widgets/command_list.py
textual_shell/widgets/console_log.py
textual_shell/widgets/job_manager.py
textual_shell/widgets/settings.py
textual_shell/widgets/shell_area.py
textual_shell/widgets/shell/__init__.py
textual_shell/widgets/shell/base_shell.py
textual_shell/widgets/shell/prompt.py
textual_shell/widgets/shell/shell.py
textual_shell/widgets/shell/suggestions.py
textual_shell-0.9.91.dist-info/METADATA
textual_shell-0.9.91.dist-info/WHEEL
textual_shell-0.9.91.dist-info/licenses/LICENSE
textual_shell-0.9.91.dist-info/RECORD
