Metadata-Version: 2.4
Name: textual-shell
Version: 0.9.91
Summary: A shell widget for textual.
Project-URL: Repository, https://github.com/Jason-Lawrence/textual-shell/
Project-URL: Documentation, https://jason-lawrence.github.io/textual-shell/
Author-email: Jason Lawrence <thejasonlawrence1@gmail.com>
License: MIT License
License-File: LICENSE
Classifier: License :: OSI Approved :: MIT License
Classifier: Operating System :: OS Independent
Classifier: Programming Language :: Python :: 3
Requires-Python: >=3.8
Requires-Dist: pyyaml>=6.0.2
Requires-Dist: textual>=1.0.0
